WIMLib/Config.py
WIMLib/Shared.py
WIMLib/WiMLogging.py
WIMLib/__init__.py
WIMLib/Resources/Result.py
WIMLib/Resources/__init__.py
WIMLib/ServiceAgents/ServiceAgentBase.py
WIMLib/ServiceAgents/__init__.py
WIMLib-2.0.0.dist-info/LICENSE.md
WIMLib-2.0.0.dist-info/METADATA
WIMLib-2.0.0.dist-info/WHEEL
WIMLib-2.0.0.dist-info/top_level.txt
WIMLib-2.0.0.dist-info/RECORD
