Metadata-Version: 2.1
Name: WIMLib
Version: 2.0.0
Summary: WIMLib is a custom reusable libraries and objects for logging, and other operations, this version is confied to basin functions others to come
Home-page: https://github.com/USGS-WiM/WIMLib
Author: Jeremy K. Newson Web Informatics and Mapping
Author-email: jknewson@usgs.gov
License: Public Domain
Platform: UNKNOWN
Requires-Dist: requests
Requires-Dist: certifi
